hartreehooks/__init__.py
hartreehooks/check_missing_requirements.py
hartreehooks/check_mypy_import_errors.py
hartreehooks/check_pylint_import_errors.py
hartreehooks/utils/__init__.py
hartreehooks/utils/config_file.py
hartreehooks/utils/hook.py
hartreehooks/utils/pyproject_file.py
hartreehooks/utils/setup_file.py
hartreehooks-0.3.7.dist-info/LICENSE
hartreehooks-0.3.7.dist-info/METADATA
hartreehooks-0.3.7.dist-info/WHEEL
hartreehooks-0.3.7.dist-info/entry_points.txt
hartreehooks-0.3.7.dist-info/RECORD
